<artikel>
	<id>EKO_TA_06_903</id>
	<judul>Ikut "Tax Amnesty", Bos Alfamart Bisa Tidur Tenang</judul>
	<tanggal>30/09/16</tanggal>
	<kata_kunci>tax amnesty</kata_kunci>
	<isi>Bos Alfamart Djoko Susanto mendatangi Kantor Pusat Direktorat Jenderal Pajak untuk melaporkan harta dalam rangka program pengampunan pajak atau tax amnesty. Menurutnya, program tax amnesty merupakan peluang para pengusaha untuk melaporkan harta yang selama ini belum dilaporkan. "Pokoknya kami (pengusaha) bisa tidur tenang," ujar Djoko sembari tersenyum di Kantor Pusat Ditjen Pajak, Jakarta, Jumat (30/9/2016). Djoko sendiri mengaku sudah melaporkan seluruh hartanya atas nama pribadi dan perusahaan. Semua harta itu merupakan harta yang ada di dalam negeri. "Deklarasi, saya enggak repatriasi, karena semua juga rupiah semua," kata dia. Saat ini Alfamart sudah memiliki 12.000 gerai diseluruh Indonesia. Dari jumlah itu, sekitar 3.000 gerai merupakan waralaba. Menurut Djoko, sekitar 9.000 gerai Alfamart yang bukan waralaba sudah tercatat di 300 Kantor Pelayanan Pajak (KPP) diseluruh Indonesia.</isi>
	<link>http://bisniskeuangan.kompas.com/read/2016/09/30/191800026/ikut.tax.amnesty.bos.alfamart.bisa.tidur.tenang</link>
</artikel>