<artikel>
	<id>EKO_TA_06_415</id>
	<judul>Tax Amnesty Muluskan Dana Masuk ke Dalam Negeri</judul>
	<tanggal>11/10/16</tanggal>
	<kata_kunci>Google,Yahoo Indonesia,Tax Amnesty, Program Amnesti Pajak, BKPM</kata_kunci>
	<isi>JawaPos.com - Badan Koordinasi Penanaman Modal (BKPM) mencatatkan  realisasi investasi sepanjang kuartal III 2016 mencapai Rp 445,5 triliun. 

	Capaian  itu berarti 75 persen dari proyeksi sepanjang tahun ini sejumlah Rp 594 triliun. 

	”Kami percaya diri target investasi tahun ini akan terpenuhi. Waktu tersisa masih sangat cukup untuk memenuhi kuota tersebut,” tutur Deputi Bidang Pengendalian, Pelaksanaan, dan Penanaman Modal BKPM Azhar Lubis seperti dikutip Indopos, Selasa (11/10).

	Azhar mengungkapkan realisasi investasi kuartal III tahun ini  ditunjang sukses besar proyek tax amnesty periode pertama sepanjang tiga bulan terakhir. 

	Program tax amnesty tahap I mencatatkan deklarasi  harta sebesar   Rp 3.819 triliun dengan uang tebusan senilai Rp 93,4 triliun. Jejak sukses amnesti pajak membuat orang berduit tidak takut untuk investasi di Indonesia. 

	”Ini menjadi tonggak bersejarah bagi dunia investasi nasional,” beber Azhar.
	
	Di samping itu, meski Anggaran Pendapatan dan Belanja Negara Perubahan (APBNP) tahun ini dipangkas, pemerintah tetap mengamankan proyek infrastruktur. 

	Itu petanda kalau pemerintah serius membangun infrastruktur. Berkomitmen penuh untuk menjaga dan mengawal kepercayaan investor.
	</isi>
	<link>http://www.jawapos.com/read/2016/10/11/56535/tax-amnesty-muluskan-dana-masuk-ke-dalam-negeri</link>
</artikel>