<artikel>
	<id>POL_PK_01_1075</id>
	<judul>4 Tipe Demonstran Pada Aksi Damai 4 November di Depan Istana Negara</judul>
	<tanggal>05/11/16</tanggal>
	<kata_kunci>pengamant politik, kelompok aksi damai, jerat hukum untuk ahok</kata_kunci>
	<isi>Pengamat Politik dari Indo Barometer Muhammad Qodari mengungkapkan, massa yang ikut dalam aksi damai Jumat (4/11) kemarin terbagi dalam empat kelompok. Kelompok pertama adalah kaum miskin kota korban penggusuran Basuki Tjahaja Purnama alias Ahok. "Kelompok kedua adalah lawan politik Presiden Joko Widodo," ujar Qodari di Warung Daun Cikini, Jakarta Pusat, Sabtu (5/11). Ketiga, konstelasi politik nasional pasti tidak akan lepas dari konstelasi Pilkada DKI maka. Mereka adalah yang menginginkan agar Ahok segera dijerat hukum. Itu supaya langkah mereka menuju Pilgub DKI semakin ringan. "Keempat adalah kelompok masyarakat yang ingin memenjarakan Ahok atas kasus penistaan agama," pungkasnya. Sebagaimana diberitakan, kemarin demo yang mencapai ratusan ribu orang turun di jalanan menuntut Ahok segera dipenjarakan atas dugaan kasus penistaan agama. Awalnya unjuk rasa berlangsung kondusif. Namun pada malam hari tiba-tiba menjadi ricuh karena massa pendemo mulai dibubarkan petugas keamanan. Tidak terima dibubarkan, bentrokan pun terjadi. Beruntung tidak ada korban jiwa atas peristiwa mengenaskan tadi malam.</isi>
	<link>http://www.jawapos.com/read/2016/11/05/62362/4-tipe-demonstran-pada-aksi-damai-4-november-di-depan-istana-negara</link>
</artikel>