<artikel>
	<id>OLA_BT_09_560</id><!-- [OLA,POL,EKO]_[lihatdi http://bit.ly/KelompokFPSTKI2016]_01(duadigit)_001(3digit) -->
	<judul>Alasan Superliga Junior 2016 Gunakan Format Piala Thomas dan Uber</judul>
	<tanggal>16/11/16</tanggal> <!-- DD/MM/YY -->
	<kata_kunci>superliga junior</kata_kunci>
	<kata_kunci>format</kata_kunci>
	<kata_kunci>thomas uber</kata_kunci>
	<isi>
		JawaPos.com - Turnamen anyar garapan PBSI, Blibli.com Li-Ning Superliga Junior 2016 akan menggunakan format Piala Thomas dan Uber.

Kepala Bidang Pengembangan Demisioner PBSI, Basri Yusuf membeberkan alasan penggunaan format tersebut. Menurutnya, hal itu untuk melengkapi turnamen yang selama ini sudah ada di Indonesia.

"Superliga Junior 2016 ini menggunakan sistem Piala Thomas dan Uber supaya bisa melengkapi kalender yang sudah ada sebelumnya," kata Basri di Jakarta, Rabu (16/11).

"Karena sistem beregu campuran atau seperti yang digunakan di Piala Sudirman sudah ada di Jaya Raya Pengembangan Cup," sambungnya.

Tercatat ada delapan tim putra dan tujuh tim putri yang akan bertarung untuk memperbutkan Piala Liem Swie King dan Susy Susanti. Pemberian nama turnamen tersebut juga bukan tanpa alasan.

Prestasi King dan Susy menjadi alasan PBSI menggunakan nama dua legenda bulu tangkis tersebut menjadi nama Piala. King tercatat berhasil merebut tiga gelar Piala Thomas, sementara Susy meraih dua gelar Piala Uber.

Superliga Junior 2016 sendiri akan digelar pada 21-16 November mendatang, di GOR Djarum Magelang, Jawa Tengah. Total hadiah yang akan diperebutkan pada turnamen tersebut bernilan Rp 200 Juta untuk masing-masing sektor. (zul/JPG)
	</isi><!-- Gak usah tag paragraf -->

	<link>http://www.jawapos.com/read/2016/11/16/64720/alasan-superliga-junior-2016-gunakan-format-piala-thomas-dan-uber</link>
</artikel>