<artikel>
	<id>OLA_BT_09_521</id><!-- [OLA,POL,EKO]_[lihatdi http://bit.ly/KelompokFPSTKI2016]_01(duadigit)_001(3digit) -->
	<judul>Tunggal Putri Pastikan Tempat di Final Bulutangkis SEA Games</judul>
	<tanggal>15/06/2015</tanggal> <!-- DD/MM/YY -->
	<kata_kunci>Tunggal Putri</kata_kunci>
	<kata_kunci>Final</kata_kunci>
	<kata_kunci>SEA Games</kata_kunci>
	<isi>
		VIVA.co.id - Langkah pasangan Praveen Jordan/Debby Susanto yang melaju ke babak final bulutangkis SEA Games 2015, Singapura, berhasil diikuti oleh pemain putri muda berbakat, Hana Ramadhini.

Menghadapi tunggal putri Malaysia, Goh Jin Wei, Hana yang sempat tertekan di set pertama, mampu membalikan kedudukan untuk menang 16-21, 21-12 dan 21-18 dalam laga yang di gelar di  lapangan 2 Singapore Indoor Stadium, Senin, 15 Juni 2015.

Meski bukan yang favoritkan untuk maju ke final, Hana tidak terpengaruh dengan hal tersebut dengan terus memberikan perlawanan sengit kepada Goh. 

Tampil ngotot sepanjang permainan, Hana akhirnya kembali menjawab tantangan yang dipercayakan padanya pasca tersingkirnya Lindaweni Fanetri di perempat final kemarin.

Di final besok Hana sudah ditunggu oleh tunggal putri Thailand, Busanan Ongbumrungpan. Dari rekor pertemuan mereka berdua, Hana baru sekali takluk dari Busanan kala bertemu di ajang World Junior Championships 2013.
 
Dengan demikian, Indonesia sejauh ini telah menempatkan dua wakilnya di dua sektor berbeda, ganda campuran dan tunggal putri. 

Sementara dua wakil Merah Putih yang harus tersingkir di semifinal hari ini adalah pasangan mixed doubles, Riky Widianto/Richi Puspita Dili dan duet putri, Anggia Shitta Awanda/Ni Ketut Mahadewi Istarani yang takluk dari para ganda asal Malaysia.
	</isi><!-- Gak usah tag paragraf -->

	<link>http://sport.viva.co.id/news/read/638447-tunggal-putri-pastikan-tempat-di-final-bulutangkis-sea-games</link>
</artikel>