<artikel>
	<id>OLA_BT_09_377</id>
	<judul>Anggia/Tiara Kalah, Indonesia Ditekuk Thailand di Piala Uber</judul>
	<tanggal>17/05/16</tanggal>
	<kata_kunci>Olahraga, bulutangkis, piala uber, Anggia Shitta Awanda,Tiara Rosalia Nuraidah</kata_kunci>
	<isi>Pasangan ganda putri Indonesia, Anggia Shitta Awanda/Tiara Rosalia Nuraidah, gagal menyelamatkan Indonesia dari kekalahan melawan Thailand dalam pertandingan terakhir Grup C Piala Uber 2016 di Kunshan, Cina, Selasa, 17 Mei 2016. Anggia/Tiara dikalahkan Jongkolphan Kititharakul/Rawinda Prajongjai 14-21, 21-17, 24-22.

Indonesia sebelumnya tertinggal 1-2 dari Thailand setelah Hanna Ramadhini dikalahkan Busanan Ongbumrungphan di partai ketiga dan Maria Febe Kusumastuti oleh Ratchanok Intanon di partai pertama. Indonesia mendapatkan satu poin berkat kemenangan Della Destiara Haris/Rosyita Eka Putri Sari atas Sapsiree Taerattanachai/Puttita Supajirakul.

Sekalipun kalah oleh Thailand, Indonesia tetap lolos ke perempat final Piala Uber 2016. Sebab, tim Merah-Putih menjadi runner-up Grup C. 

Sebenarnya, dalam pertarungan melawan Thailand ini, Indonesia mengandalkan dua pasangan gandanya dan berharap satu pemain tunggal putri bisa mencuri poin dari Thailand, yang memang memiliki pemain tunggal dengan kekuatan merata. 
</isi>
	<link>https://sport.tempo.co/read/news/2016/05/17/100771734/anggia-tiara-kalah-indonesia-ditekuk-thailand-di-piala-uber</link>
</artikel>