<artikel>
  <id>OLA_PON_11_594</id>
  <judul>Api Pon XIX Tiba di Bogor</judul>
  <tanggal>14/09/16</tanggal>
  <kata_kunci></kata_kunci>
  <isi>n XIX Tiba di Bogor

VIVA.co.id &#8211; Kota Bogor terpilih menjadi satu dari 13 kota yang terpilih menjadi tempat persemayaman kirab api Pekan Olahraga Nasional (PON) XIX tahun 2016. Kirab obor api PON XIX tiba di Bogor, Jawa Barat, diterima langsung oleh Walikota Bogot, Bima Arya. Kirab api PON Jabar 2016 kembali diberangkatkan menuju Alun-alun Kabupaten Sukabumi dan Lapangan Merdeka, Kota Sukabumi.</isi>
  <link>http://foto.viva.co.id/read/16660-api-pon-xix-tiba-di-bogor</link>
</artikel>
