<?xml version="1.0"?>
<artikel>
<id>OLA_PO_11_044</id>
<judul>Insiden Laser, Sulsel Tolak Medali Perak Sepak Bola PON Jabar</judul>
<tanggal>28/09/2016</tanggal>
<kata_kunci>Kata Kunci berita</kata_kunci>
<isi>Liputan6.com, Bandung - Tim Sepak bola Sulawesi Selatan menolak upacara penyerahan medali PON Jabar 2016.
Keputusan itu terkait insiden sinar laser yang terjadi dalam laga final yang berlangsung di Si Jalak Harupat, Soreang, Kabupaten Bandung, Rabu (28/9/2016).
Tim sepak bola Jawa Barat menang dalam adu penalti dengan skor 5-4, usai bermain 0-0 selama 120 menit. Dalam drama adu penalti itu, dua algojo Sulsel gagal, Irfan Irfandi dan Alia Alfuad.
Ketika upacara pengalungan medali, Sulses memilih tidak hadir seusai laga. Mereka tidak kembali ke lapangan dan memilih masuk ruang ganti.
Ketua Asosiasi Provinsi (Asprov) PSSI Sulsel, Mulyadi, keberatan diajukan karena sinar laser yang mengarah ke penendang penalti. Menurut dia, hal tersebut mengganhgu konsentrasi para pemain Sulsel saat babak tos-tosan.
"Dua penendang kami tadi dilaser, komentator di televisi pun juga sudah bilang. Ini hasil yang tidak sportif, Gubernur harus minta maaf, kami tidak ikut upacara," paparnya.
Belum bisa dipastikan apakah Sulsel akan mengajukan protes ke Dewan Hakim PB PON. Namun, fakta ini jelas menambah daftar panjang kontroversi selama PON Jabar berlangsung.</isi>
<link>http://bola.liputan6.com/read/2613481/insiden-laser-sulsel-tolak-medali-perak-sepak-bola-pon-jabar?source=search</link>
</artikel>