<artikel>
	<id>OLA_GP_01_039</id>
	<judul>Rossi Pole Position, Marquez Start Kedua di GP Jepang</judul>
	<tanggal>15/10/16</tanggal>
	<kata_kunci>kualifikasi, pebalap, tercepat, musim ini, pole position</kata_kunci>
	<isi>Setelah mencatat hasil buruk di sesi latihan bebas, Valentino Rossi tampil menggebrak saat babak kualifikasi bergulir. The Doctor sukses jadi pebalap tercepat dan berhak atas pole position pada lomba esok. Rossi menjadi pebalap tercepat di babak kualifikasi dengan catatan waktu 1 menit, 43,954 detik, mengungguli Marquez yang merupakan rival kuatnya musim ini. Marquez sejatinya merupakan favorit untuk mendapatkan pole position namun ia sempat terjatuh di sesi kualifikasi. Catatan waktu terbaik Marquez di sesi kualifikasi tertinggal 0,180 detik lebih lambat dari Rossi. Rekan Rossi di Yamaha, Jorge Lorenzo, mencatat waktu terbaik ketiga dan bakal melengkapi formasi baris pertama di GP Jepang nanti. Keberhasilan Lorenzo start di baris depan tentunya merupakan sebuah kejutan mengingat ia baru saja mengalami kecelakaan di sesi latihan bebas. Marquez saat ini menguasai puncak klasemen sementara dengan selisih 52 poin atas Rossi. Namun Rossi sendiri bertekad untuk tak menyerah begitu saja dan bakal terus tampil maksimal di sisa musim ini.</isi>
	<link>http://www.cnnindonesia.com/olahraga/20161015130225-156-165692/rossi-pole-position-marquez-start-kedua-di-gp-jepang/</link>
</artikel>
