<artikel>
	<id>OLA_GP_01_109</id>
	<judul>Marquez Taklukkan Rossi di Aragon</judul>
	<tanggal>25/09/16</tanggal>
	<kata_kunci>aragon, kemenangan, juara dunia</kata_kunci>
	<isi>Marc Marquez akhirnya berhasil menaklukkan Valentino Rossi di GP Aragon. Kemenangan itu juga berarti peluang Marquez jadi juara dunia MotoGP musim ini bakal makin besar. Marquez yang memulai lomba di pole position sempat membuat kesalahan dan terlempar ke posisi kelima saat perlombaan memasuki lap ketiga. Namun perlahan tapi pasti, Marquez mampu mendahului Andrea Dovizioso, Maverick Vinales, Jorge Lorenzo, dan Valentino Rossi yang ada di depannya. Setelah mendahului Rossi, Marquez bahkan tak teradang lagi untuk jadi yang pertama menyentuh garis finis. Kemenangan ini merupakan kemenangan keempat Marquez di MotoGP musim ini setelah sebelumnya ia berjaya di Argentina, Amerika Serikat, dan Jerman. Tak hanya itu, kemenangan ini juga membuat Marquez kini unggul 52 angka atas Rossi dengan empat seri tersisa. Tanpa kesalahan besar yang dilakukan, Marquez berpeluang besar menjadi juara dunia musim ini.</isi>
	<link>http://www.cnnindonesia.com/olahraga/20160925195544-156-161035/marquez-taklukkan-rossi-di-aragon/</link>
</artikel>
