<artikel>
	<id>POL_PP_02_314</id>
	<judul>SBY Jadi Ketua Umum agar Demokrat Tak Diintervensi Pemerintah</judul>
	<tanggal>12/5/15</tanggal>
	<kata_kunci> KetumDemokrat,Demokrat,SBY</kata_kunci>
	<isi>
Ketua Dewan Pimpinan Pusat Demokrat Ulil Abshar Abdalla menyatakan kader Demokrat khawatir akan adanya intervensi pemerintah untuk memecah-belah partainya. Oleh sebab itu, ujar Ulil, para kader memutuskan untuk kembali memilih Susilo Bambang Yudhoyono sebagai ketua umum partai.

Dalam konferensi pers di lokasi Kongres IV Demokrat, Hotel Shangri-La, Surabaya, Ulil menyatakan ada intervensi pemerintah melalui oknum-oknum internal Demokrat. Pola itu pula, kata Ulil, yang menimpa Partai Golkar dan Partai Persatuan Pembangunan.
"Hal ini begitu seriusnya sehingga menimbulkan reaksi keras dari Pak SBY," kata Ulil.

Hal itu pula, menurut Ulil, yang membuat Demokrat belum bisa melakukan regenerasi kepemimpinan partai sebagaimana mestinya. Regenerasi diharapkan dapat terjadi pada periode berikutnya.

“Sekarang kami mohon maaf belum bisa melakukan itu (regenerasi). Pak SBY tetap jadi ketua umum," ujarnya.

Ulil mengatakan figur SBY amat penting untuk menangkal intervensi dari luar, sebab Presiden RI keenam itu dianggap sebagai tokoh yang dapat menjaga keutuhan partai. “Kalau tak ada tokoh kuat, akan banyak juga ancaman internal,” kata dia.

SBY saat ini resmi menjadi calon tunggal Ketua Umum Demokrat. Tak ada kader selain SBY yang mendaftarkan diri sebagai calon ketua umum hingga pendaftaran ditutup siang ini. 

	</isi>
	<link>http://www.cnnindonesia.com/politik/20150512143443-32-52794/sby-jadi-ketua-umum-agar-demokrat-tak-diintervensi-pemerintah/</link>
</artikel>