<artikel>
	<id>POL_PP_02_148</id>
	<judul>Golkar Ingatkan Elite Jangan Sampai Ribut di Publik</judul>
	<tanggal>21/10/16</tanggal>
	<kata_kunci>golkar, jokowi jk, Partai Politik</kata_kunci>
	<isi>
	Setelah penyelenggaraan musyawarah nasional luar biasa (munaslub) dan rapat kerja nasional (rakernas) beberapa waktu lalu, Partai Golkar telah menegaskan posisinya dalam mendukung pemerintahan Presiden Joko Widodo (Jokowi)-Jusuf Kalla (JK).

	Ketua DPP Golkar Zainuddin Amali mengingatkan bahwa posisi ini harus dipatuhi hingga tingkat terbawah. Kader juga diminta mengambil sikap selaras dengan arahan partai.

	"Kebijakan mendukung pemerintah bukan hanya di tingkat pusat, tetapi di seluruh tingkatan. Apakah gubernur, bupati, wali kota dari Golkar," kata Zainuddin Amali di Senayan, Jakarta, Jumat, 21 Oktober 2016.

	Apabila ada yang masih menentang garis partai, dia berharap kader bisa berkomunikasi dengan baik secara internal terlebih dahulu. "Jangan mempertontonkan pada rakyat seolah-olah kita berhantam," ujar Anggota Komisi I DPR ini.

	Amali mengakui, setelah Golkar menyatakan mendukung pemerintah, masih ada sejumlah kader di daerah yang belum menerima hal tersebut. Oleh karena itu, Golkar kembali telah mengumpulkan elite-elite partai dari pusat hingga daerah untuk menyamakan persepsi dukungan terhadap pemerintah.

	"Ada sisanya yang belum paham itu. Makanya yang kemarin kami kumpulkan eksekutif dan legislatif yang kemarin itu untuk membicarakan kebijakan itu. Dari nasional sampai kabupaten-kota," kata Amali.
	</isi>
	<link>http://politik.news.viva.co.id/news/read/837552-golkar-ingatkan-elite-jangan-sampai-ribut-di-publik</link>
</artikel>