<artikel>
	<id>POL_PP_02_141</id>
	<judul>Golkar Klaim Elektabilitas Ahok Kembali Menguat</judul>
	<tanggal>23/10/16</tanggal>
	<kata_kunci>elektabilitas ahok, DPP Golkar, pilkada</kata_kunci>
	<isi>
	Ketua DPD DKI Jakarta Partai Golkar, Fayakhun Andriadi mengklaim posisi Basuki Tjahaja Purnama atau Ahok dalam hasil survei berbagai lembaga telah kembali menguat.

	"Bung Ahok posisinya sudah mulai kembali menguat, lalu pasangan calon yang lain terjadi peta, siapa yang lebih unggul. Siapa yang lebih sedang bersaing satu sama lain," kata Fayakhun di lapangan eks Golf Driving Range, Jakarta, Minggu 23 Oktober 2016.

	Ia menjelaskan semula berdasarkan survei sejumlah lembaga Ahok mendapatkan elektabilitas tinggi karena calon lainnya belum terlihat. Lalu saat pendaftaran calon, elektabilitas Ahok berubah karena responden pasti menilai dulu calon lain yang muncul.

	"Begitu ada pasangan calon dua lagi, tentu publik menilai, nah pada saat itu kita bisa melihat itu. Voternya (pemilih) membesar dan Bung Ahok menurun," kata Fayakhun.

	Ia menambahkan meski sempat turun, elektabilitas Ahok kini menguat. Meski begitu, ia tak menafikkan persoalan elektabilitas para kandidat masih sangat dinamis.

	"Kita akan melihat terus dan Golkar akan terus berjuang sampai dengan hari pemilihan," kata Fayakhun.
	</isi>
	<link>http://metro.news.viva.co.id/news/read/838334-golkar-klaim-elektabilitas-ahok-kembali-menguat</link>
</artikel>