<artikel>
	<id>EKO_IN_07_635</id>
	<judul>PM Singapura Lee Hsien Loong Nilai RI Mitra Penting </judul>
	<tanggal>15/11/16</tanggal>
	<kata_kunci>investor terbesar</kata_kunci>
	<isi>
		Perdana Menteri Singapura, Lee Hsien Loong mengatakan, Indonesia merupakan mitra penting bagi Singapura.

		Selama dua tahun terakhir, Singapura tercatat sebagai negara yang menanamkan investasi asing langsung atau foreign direct investment (FDI) terbesar di Indonesia.

		Lewat pengembangan KIK, Lee berharap, para pengusaha semakin percaya menjadikan Indonesia sebagai negara tujuan investasi.

		"Dengan ada KIK ini akan semakin menarik perhatian investor Singapura dan merupakan win-win proyek bagi kedua negara," ujar Lee, seperti dikutip dari Antara, Selasa (15/11/2016).

		Lee menyampaikan hal itu usai meresmikan Kawasan Industri Kendal (KIK) Park by the Bay bersama Presiden Joko Widodo dan Menteri Perindustrian Airlangga Hartarto di Semarang, Jawa Tengah.

		Lee menuturkan, pengusaha Singapura tidak hanya menanamkan modalnya di Batam-Bintan-Karimun (BBK) Kepulauan Riau, tetapi juga daerah lain di Indonesia termasuk di KIK.

		Pembangunan KIK juga diharapkan dapat menaikkan pertumbuhan ekonomi di Jawa Tengah, sejalan dengan meningkatnya aktivitas industri di kawasan tersebut.

		Gubernur Jawa Tengah Ganjar Pranomo menegaskan, pihaknya siap mendukung pengembangan KIK dengan memberikan kemudahan perizinan investasi serta penyediaan tenaga kerja terdidik dan terampil.
	</isi>
	<link>http://bisnis.liputan6.com/read/2652613/pm-singapura-lee-hsien-loong-nilai-ri-mitra-penting</link>
</artikel>