<artikel>
<id>EKO_EI_05_756</id>
<judul>Trump Menang Pemilu AS, Gubernur BI: Ekspor Indonesia Akan</judul>
<tanggal>10/11/16</tanggal>
<kata_kunci>trump,menang,pemilu,as,gubernur,bi,ekspor,indonesia</kata_kunci>
<isi> Selain itu, yang perlu diamati adalah proteksionisme. Trump menyatakan ketidakpuasannya terhadap kondisi perekonomian saat ini dan kebijakan proteksionisme merupakan jalan keluar.    "Amerika lebih protektif. Antara lain terlihat akan dilakukannya negosiasi  North American Free Trade Agreement  (Nafta), TPP ( Trans Pasific Partnership ) tidak akan diteruskan. Negara-negara besar akan mendapatkan  presssure ," ungkapnya.   Yang terakhir adalah upayanya untuk menekan pertumbuhan ekonomi global. Globalisasi dianggap lebih banyak mendatangkan duka ketimbang suka. Misalnya, impor barang konsumsi yang murah telah menyebabkan rendahnya gaji pekerja domestik.    "Ini dorongan perubahan. Ini kebijakan yang harus kita lihat lagi bagaimana ke depan. Kebijakan-kebijakan protektif ini akan berdampak ke Indonesia, karena Amerika termasuk terbesar ekspornya," tutur dia.   "Kebijakan protektif ini juga akan membatasi ekspor negara seperti Tiongkok yang akan dibatasi. Kalau ekspor dibatasi, tentu impor dari Indonesia juga akan berdampak. Dan ketidakpastian global juga akan berdampak kepada Indonesia," pungkasnya.</isi>
<link>http://finance.detik.com/ekonomi-bisnis/3342621/trump-menang-pemilu-as-gubernur-bi-ekspor-indonesia-akan-terpengaruh
</link>
</artikel>